anime_reference/Naruto.py
anime_reference/__init__.py
anime_reference/anime.py
anime_reference/constants.py
anime_reference/utils.py
anime_reference/anime_objects/Anime.py
anime_reference/anime_objects/AttackOnTitan.py
anime_reference/anime_objects/Naruto.py
anime_reference/anime_objects/__init__.py
anime_reference/anime_objects/constants.py
anime_reference/anime_objects/utils.py
anime_reference-0.0.14.dist-info/METADATA
anime_reference-0.0.14.dist-info/WHEEL
anime_reference-0.0.14.dist-info/top_level.txt
anime_reference-0.0.14.dist-info/RECORD
