Metadata-Version: 2.1
Name: anime-reference
Version: 0.0.14
Summary: A reference package for all things anime.
Home-page: https://github.com/Matt711/anime_reference
Author: Matt Murray
Author-email: matthewmurray711@gmail.com
License: MIT
Keywords: fandom anime,manga,data mining,anime,anime reference,manga reference
Platform: UNKNOWN
Classifier: Programming Language :: Python :: 3
Classifier: License :: OSI Approved :: MIT License
Classifier: Operating System :: OS Independent
Requires-Python: >=3.6
Requires-Dist: beautifulsoup4 (==4.9.3)
Requires-Dist: requests (==2.25.1)
Requires-Dist: pandas (==1.2.4)
Requires-Dist: lxml (==4.6.3)
Requires-Dist: html5lib (==1.1)
